automyte/PLANS.md
automyte/__about__.py
automyte/__init__.py
automyte/main.py
automyte/automaton/__init__.py
automyte/automaton/automaton.py
automyte/automaton/flow.py
automyte/automaton/run_context.py
automyte/automaton/types.py
automyte/config/__init__.py
automyte/config/config.py
automyte/config/fields.py
automyte/config/vcs.py
automyte/config/mappers/__init__.py
automyte/config/mappers/cmd.py
automyte/config/mappers/env.py
automyte/config/mappers/file.py
automyte/discovery/__init__.py
automyte/discovery/explorers/__init__.py
automyte/discovery/explorers/base.py
automyte/discovery/explorers/local_files.py
automyte/discovery/file/__init__.py
automyte/discovery/file/base.py
automyte/discovery/file/os_file.py
automyte/discovery/filters/__init__.py
automyte/discovery/filters/base.py
automyte/discovery/filters/contains.py
automyte/discovery/filters/path.py
automyte/history/__init__.py
automyte/history/base.py
automyte/history/in_file.py
automyte/history/in_memory.py
automyte/history/types.py
automyte/project/__init__.py
automyte/project/project.py
automyte/project/types.py
automyte/tasks/__init__.py
automyte/tasks/vcs.py
automyte/tasks/flow_control/__init__.py
automyte/tasks/flow_control/conditionals.py
automyte/tasks/flow_control/guards.py
automyte/tasks/flow_control/lifecycle.py
automyte/tasks/utils/__init__.py
automyte/tasks/utils/breakpoint.py
automyte/tasks/utils/filesystem.py
automyte/utils/bash.py
automyte/utils/filesystem.py
automyte/utils/random.py
automyte/vcs/__init__.py
automyte/vcs/base.py
automyte/vcs/git.py
automyte-0.2.0.dist-info/METADATA
automyte-0.2.0.dist-info/WHEEL
automyte-0.2.0.dist-info/entry_points.txt
automyte-0.2.0.dist-info/licenses/LICENSE
automyte-0.2.0.dist-info/RECORD
